parsley_coco/__init__.py
parsley_coco/alternative_dataclasses.py
parsley_coco/factory.py
parsley_coco/logger.py
parsley_coco/parser.py
parsley_coco/py.typed
parsley_coco/recursive_dataclass_with_path_to_yaml.py
parsley_coco/sentinels.py
parsley_coco/utils.py
parsley_coco/data/yaml_files/test_b.yaml
parsley_coco-0.1.31.dist-info/licenses/LICENSE
tests_parsley/tes_combinedexample.py
tests_parsley/test_all_features.py
tests_parsley/test_basic.py
tests_parsley/test_command_line.py
tests_parsley/test_configfile.py
tests_parsley/test_extra_args.py
tests_parsley/test_int_dataclass.py
tests_parsley/test_overwrite.py
tests_parsley/test_parse_arguments.py
tests_parsley/test_readme.py
tests_parsley/test_recursive_dataclass_with_path_to_yaml.py
tests_parsley/test_tag.py
tests_parsley/test_utils.py
parsley_coco-0.1.31.dist-info/METADATA
parsley_coco-0.1.31.dist-info/WHEEL
parsley_coco-0.1.31.dist-info/top_level.txt
parsley_coco-0.1.31.dist-info/RECORD
