Metadata-Version: 2.4
Name: parsley-coco
Version: 0.1.31
Summary: A parser combining dacite and argparse
Author-email: Victor Gabillon <victorgabillon@gmail.com>
License-Expression: GPL-3.0-only
Project-URL: Homepage, https://github.com/victorgabillon/parsley
Requires-Python: >=3.12
License-File: LICENSE
Requires-Dist: PyYAML>=6.0.2
Requires-Dist: dacite>=1.9.2
Requires-Dist: click==8.1.8
Provides-Extra: test
Requires-Dist: pytest>=7.0; extra == "test"
Requires-Dist: types-PyYAML; extra == "test"
Dynamic: license-file
